MANIFEST.in
README.rst
setup.py
mvassconvert/__init__.py
mvassconvert/accelerationFactors.txt
mvassconvert/accelerationReverse.txt
mvassconvert/angleFactors.txt
mvassconvert/angleReverse.txt
mvassconvert/areaDensityFactors.txt
mvassconvert/areaDensityReverse.txt
mvassconvert/areaFactors.txt
mvassconvert/areaReverse.txt
mvassconvert/chemicalAmountFactors.txt
mvassconvert/chemicalAmountReverse.txt
mvassconvert/currencyLetters.txt
mvassconvert/dataBandwidthFactors.txt
mvassconvert/dataBandwidthReverse.txt
mvassconvert/dataStorageFactors.txt
mvassconvert/dataStorageReverse.txt
mvassconvert/densityFactors.txt
mvassconvert/densityReverse.txt
mvassconvert/electricChargeFactors.txt
mvassconvert/electricChargeReverse.txt
mvassconvert/electricCurrentFactors.txt
mvassconvert/electricCurrentReverse.txt
mvassconvert/ewhFactors.txt
mvassconvert/ewhReverse.txt
mvassconvert/flowFactors.txt
mvassconvert/flowReverse.txt
mvassconvert/forceFactors.txt
mvassconvert/forcereverse.txt
mvassconvert/frequencyFactors.txt
mvassconvert/frequencyReverse.txt
mvassconvert/fuelEconomyFactors.txt
mvassconvert/fuelEconomyReverse.txt
mvassconvert/illuminanceFactors.txt
mvassconvert/illuminanceReverse.txt
mvassconvert/lengthFactors.txt
mvassconvert/lengthReverse.txt
mvassconvert/luminanceFactors.txt
mvassconvert/luminanceReverse.txt
mvassconvert/luminousIntensityFactors.txt
mvassconvert/luminousIntensityReverse.txt
mvassconvert/massFactors.txt
mvassconvert/massFlowFactors.txt
mvassconvert/massFlowReverse.txt
mvassconvert/massReverse.txt
mvassconvert/powerFactors.txt
mvassconvert/powerReverse.txt
mvassconvert/pressureFactors.txt
mvassconvert/pressureReverse.txt
mvassconvert/speedFactors.txt
mvassconvert/speedReverse.txt
mvassconvert/tempFactors.txt
mvassconvert/tempReverse.txt
mvassconvert/timeFactors.txt
mvassconvert/timeReverse.txt
mvassconvert/torqueFactors.txt
mvassconvert/torquereverse.txt
mvassconvert/volumeFactors.txt
mvassconvert/volumeReverse.txt
mvassconvert.egg-info/PKG-INFO
mvassconvert.egg-info/SOURCES.txt
mvassconvert.egg-info/dependency_links.txt
mvassconvert.egg-info/top_level.txt