Metadata-Version: 1.1
Name: mvassconvert
Version: 1.3.1
Summary: A package that allows the user to convert 1000+ different units
Home-page: UNKNOWN
Author: Matthew Vasseur
Author-email: mvasseur22@students.hopkins.edu
License: UNKNOWN
Platform: UNKNOWN
Classifier: Programming Language :: Python :: 3
Classifier: License :: OSI Approved :: MIT License
Classifier: Operating System :: OS Independent
